{
    "locais": [
      {
        "id": 1,
        "estado": "sp",
        "municipio": "são Paulo"
      },
       {
        "id": 2,
        "estado": "sp",
        "municipio": "sorocaba"
      },
       {
        "id": 3,
        "estado": "rj",
        "Mmunicipio": "rio de janeiro"
      },
       {
        "id": 4,
        "estado": "rj",
        "municipio": "niteroi"
      }
    ],
  
    
    
    
    "preco": [
      {
        "id": 1,
        "sala": "n 3d",
        "valor":"R$ 30,00",
        "local": "sp são paulo"
      },
      
       {
        "id": 2,
        "sala": "g 3d",
        "valor":"R$ 40,00",
        "local": "sp são paulo"
      },
       {
        "id": 1,
        "sala": "n 3d",
        "valor":"R$ 25,00",
        "local": "sp sorocaba"
      },
       {
        "id": 1,
        "sala": "g 3d",
        "valor":"R$ 30,00",
        "local": "rj rio de janeiro"
      }
      
      
    ],
  
    
    
    
    "catalogo": [
      {
        "id": 1,
        "titulo": "Filme 1",
         "sala": "G 3D",
        "preço":"R$ 30,00"
      },
      
       {
        "id": 2,
        "titulo": "Filme 2",
         "sala": "N 3D",
        "sreço":"R$ 25,00"
      },
      
       {
        "id": 3,
        "titulo": "Filme 3",
         "sala": "M 2D",
        "preço":"R$ 35,00"
      },
      
       {
        "id": 4,
        "titulo": "Filme 4",
         "sala": "VIP 3D",
        "preço":"R$ 60,00" 
      }
  
    
    ]
  }
  
